{
  "collectionName": "components_shared_seos",
  "info": {
    "displayName": "SEO",
    "icon": "doctor"
  },
  "options": {},
  "attributes": {
    "metaTitle": {
      "type": "string",
      "required": true
    },
    "metaDescription": {
      "type": "text",
      "required": true
    },
    "metaImage": {
      "type": "media",
      "multiple": true,
      "required": true,
      "allowedTypes": [
        "images",
        "files",
        "videos",
        "audios"
      ]
    },
    "keywords": {
      "type": "string"
    },
    "canonicalURL": {
      "type": "string",
      "required": true
    }
  },
  "config": {}
}
